{
    "configurations": [
        {
            "name": "Win32",
            "includePath": [
                "${env:USERPROFILE}\\Documents\\Arduino\\libraries\\SocketIoClient",
                "${env:USERPROFILE}\\Documents\\Arduino\\hardware\\esp8266com\\esp8266\\**",
                "${env:USERPROFILE}\\Documents\\Arduino\\libraries\\ArduinoJson\\src",
                "C:\\Program Files (x86)\\Arduino\\hardware\\**",
                "C:/Users/thongnmtran/Documents/Arduino/hardware/**",
                "${env:USERPROFILE}\\Documents\\Arduino\\libraries\\**",
                "C:\\Program Files (x86)\\Arduino\\libraries\\**",
                "${workspaceFolder}/core/**"
            ],
            "intelliSenseMode": "msvc-x64",
            "forcedInclude": [],
            "cStandard": "c11",
            "cppStandard": "c++11"
        }
    ],
    "version": 4
}